<?xml version="1.0" encoding="UTF-8"?>
<beans xmlns="http://www.springframework.org/schema/beans"
	xmlns:xsi="http://www.w3.org/2001/XMLSchema-instance"
	xsi:schemaLocation="http://www.springframework.org/schema/beans http://www.springframework.org/schema/beans/spring-beans.xsd">
	
	<!-- Root Context: defines shared resources visible to all other web components -->
	<!--  datasoruce -->
    <bean id="dataSource" class="org.apache.commons.dbcp.BasicDataSource">
        <property name="driverClassName" value="com.mysql.jdbc.Driver"/>
        <property name="url" value="jdbc:mysql://localhost:3306/team_board?useUnicode=true&amp;characterEncoding=EUC-KR"/>
        <property name="username" value="root"/>
        <property name="password" value="java0000"/> 
    </bean>
   
    <!-- transaction manager -->    
    <bean id="transactionManager" class="org.springframework.jdbc.datasource.DataSourceTransactionManager">
        <property name="dataSource" ref="dataSource" />
    </bean>
   
    <!-- mybatis -->
    <bean id="sqlSessionFactoryArt" class="org.mybatis.spring.SqlSessionFactoryBean">
        <property name="dataSource" ref="dataSource" />
        <property name="mapperLocations" value="classpath:com/cafe24/ksmart02/repository/articleMapper.xml"/>
    </bean>
     <bean id="sqlSessionArt" class="org.mybatis.spring.SqlSessionTemplate">
        <constructor-arg index="0" ref="sqlSessionFactoryArt" />
    </bean>
    
     <bean id="sqlSessionFactoryCom" class="org.mybatis.spring.SqlSessionFactoryBean">
        <property name="dataSource" ref="dataSource" />
        <property name="mapperLocations" value="classpath:com/cafe24/ksmart02/repository/commentMapper.xml"/>     
    </bean>
    <bean id="sqlSessionCom" class="org.mybatis.spring.SqlSessionTemplate">
        <constructor-arg index="0" ref="sqlSessionFactoryCom" />
    </bean>
</beans>
